gdpr_solution/__init__.py
gdpr_solution/admin.py
gdpr_solution/app_config.py
gdpr_solution/apps.py
gdpr_solution/models.py
gdpr_solution/urls.py
gdpr_solution/views.py
gdpr_solution/wagtail_hooks.py
gdpr_solution/locale/en/LC_MESSAGES/django.po
gdpr_solution/migrations/__init__.py
gdpr_solution/templates/cookiebanner.html
gdpr_solution/templates/admin/gdpr_solution/change_list.html
gdpr_solution/templates/modeladmin/gdpr_solution/inspect.html
gdpr_solution/templatetags/__init__.py
gdpr_solution/templatetags/gdpr_solution.py
django_gdpr_solution-1.2.0.dist-info/LICENSE
django_gdpr_solution-1.2.0.dist-info/METADATA
django_gdpr_solution-1.2.0.dist-info/WHEEL
django_gdpr_solution-1.2.0.dist-info/top_level.txt
django_gdpr_solution-1.2.0.dist-info/RECORD
