Metadata-Version: 2.1
Name: django-gdpr-solution
Version: 1.2.0
Summary: Add GDPR compliant cookie consent to your website.
Home-page: https://github.com/lorenzomonte-it/django-gdpr-solution
Author: Lorenzo
License: MIT
Project-URL: Homepage, https://github.com/lorenzomonte-it/django-gdpr-solution
Platform: UNKNOWN
Classifier: License :: OSI Approved :: MIT License
Classifier: Operating System :: OS Independent
Classifier: Programming Language :: Python
Classifier: Framework :: Django
Classifier: Framework :: Wagtail
Requires-Dist: Django (>=1.11.0)
